paso/__init__.py
paso/base.py
paso/learners/__init__.py
paso/learners/learners.py
paso/post/SaliencyMap.py
paso/post/__init__.py
paso/pre/ContinuoustoCategory.py
paso/pre/EliminateUnviableFeatures.py
paso/pre/__init__.py
paso/pre/cleaners.py
paso/pre/encoders.py
paso/pre/inputers.py
paso/pre/misc.py
paso/pre/scale.py
paso/pre/scalers.py
paso/pre/tmp.py
paso/pre/toCategory.py
paso/pre/toDatetimeComponents.py
paso/pre/toutil.py
paso/viz/EDA.py
paso/viz/__init__.py
tests/__init__.py
tests/conftest.py
tests/test_base.py
tests/test_test_paso_get_logger.py
tests/test_toDataFrame.py
tests/pre/__init__.py
tests/pre/test_ContinoustoCategory.py
tests/pre/test_cleaners.py
tests/pre/test_encoder.py
tests/pre/test_inputers.py
tests/pre/test_misc.py
tests/pre/test_scaler.py
tests/pre/test_toCategory.py
tests/pre/test_toDatetimeComponents.py
tests/pre/test_to_util.py
tests/viz/__init__.py
paso-0.5.2.dist-info/LICENSE
paso-0.5.2.dist-info/METADATA
paso-0.5.2.dist-info/WHEEL
paso-0.5.2.dist-info/top_level.txt
paso-0.5.2.dist-info/RECORD
