Metadata-Version: 2.1
Name: paso
Version: 0.5.2
Summary: A python package for the entire data machine learning pipeline
Home-page: https://github.com/bcottman/paso
Author: Bruce Cottman
Author-email: dr.bruce.cottman@gmail.com
License: MIT
Download-URL: https://github.com/bcottman/paso/archive/0.2.8.tar.gz
Keywords: machine-learning,deep-learning,transformations,functional,data-analytics
Platform: UNKNOWN
Requires-Dist: attrdict (>=2.0.1)
Requires-Dist: category-encoders (>=2.0.0)
Requires-Dist: ipython (>=6.4.0)
Requires-Dist: numpy (>=1.14.0)
Requires-Dist: numba (>=0.40.0)
Requires-Dist: fancyimpute (>=0.4.1)
Requires-Dist: tqdm (>=4.28.1)
Requires-Dist: pandas (>=0.22.0)
Requires-Dist: pyarrow (>=0.11.1)
Requires-Dist: pydot-ng (>=1.0.0)
Requires-Dist: pytest (>=3.6.0)
Requires-Dist: scikit-learn (>=0.19.0)
Requires-Dist: scipy (>=1.0.0)
Requires-Dist: setuptools (>=39.2.0)
Requires-Dist: typing (>=3.6.4yaml>=0.1.7)
